anyutils/__init__.py
anyutils/decorators/__init__.py
anyutils/decorators/timer.py
anyutils-0.1.1.dist-info/licenses/LICENSE
anyutils-0.1.1.dist-info/METADATA
anyutils-0.1.1.dist-info/WHEEL
anyutils-0.1.1.dist-info/top_level.txt
anyutils-0.1.1.dist-info/RECORD
